bw_migrations/__init__.py
bw_migrations/strategies.py
bw_migrations/utils.py
bw_migrations/version.py
bw_migrations/data/exiobase-3-ecoinvent-3.6.json
bw_migrations-0.2.dist-info/LICENSE
bw_migrations-0.2.dist-info/METADATA
bw_migrations-0.2.dist-info/WHEEL
bw_migrations-0.2.dist-info/top_level.txt
bw_migrations-0.2.dist-info/RECORD
