Metadata-Version: 2.1
Name: bw-migrations
Version: 0.2
Summary: Migration data and utilities for Brightway IO and LCA in general
Home-page: https://github.com/brightway-lca/bw_migrations
Author: Chris Mutel
Author-email: cmutel@gmail.com
License: NewBSD 3-clause; LICENSE
Platform: UNKNOWN
Classifier: Development Status :: 3 - Alpha
Classifier: Intended Audience :: Science/Research
Classifier: License :: OSI Approved :: BSD License
Classifier: Operating System :: MacOS :: MacOS X
Classifier: Operating System :: Microsoft :: Windows
Classifier: Operating System :: POSIX
Classifier: Programming Language :: Python :: 3.7
Classifier: Topic :: Scientific/Engineering :: Information Analysis
Classifier: Topic :: Scientific/Engineering :: Mathematics
